subspy/__init__.py
subspy/cli.py
subspy/default_subdomains.txt
subspy/subdomain.py
subspy-2.2.3.dist-info/METADATA
subspy-2.2.3.dist-info/WHEEL
subspy-2.2.3.dist-info/entry_points.txt
subspy-2.2.3.dist-info/top_level.txt
subspy-2.2.3.dist-info/RECORD
