Metadata-Version: 2.1
Name: subspy
Version: 2.2.3
Summary: SubSpy: A tool for subdomain enumeration.
Home-page: https://mrfidal.in/cyber-security/subspy
Author: Fidal
Author-email: mrfidal@proton.me
License: MIT
Keywords: subspy,subdomain,enumeration,scanning,mrfidal,cyber security
Classifier: Development Status :: 5 - Production/Stable
Classifier: Intended Audience :: Information Technology
Classifier: Intended Audience :: System Administrators
Classifier: License :: OSI Approved :: MIT License
Classifier: Programming Language :: Python :: 3
Classifier: Programming Language :: Python :: 3.11
Classifier: Topic :: Security
Requires-Dist: requests
